fine_python_black/__init__.py
fine_python_black/action.py
fine_python_black/py.typed
fine_python_black-0.2.0.dist-info/METADATA
fine_python_black-0.2.0.dist-info/WHEEL
fine_python_black-0.2.0.dist-info/top_level.txt
fine_python_black-0.2.0.dist-info/RECORD
